fiction/__init__.py
fiction-0.0.1b0.dist-info/METADATA
fiction-0.0.1b0.dist-info/WHEEL
fiction-0.0.1b0.dist-info/licenses/LICENSE.txt
fiction-0.0.1b0.dist-info/RECORD
